glamkit_collections/__init__.py
glamkit_collections/utils.py
glamkit_collections/contrib/README
glamkit_collections/contrib/__init__.py
glamkit_collections/contrib/old_work_creator/__init__.py
glamkit_collections/contrib/old_work_creator/admin_utils.py
glamkit_collections/contrib/old_work_creator/apps.py
glamkit_collections/contrib/old_work_creator/fields.py
glamkit_collections/contrib/old_work_creator/settings.py
glamkit_collections/contrib/old_work_creator/admin/__init__.py
glamkit_collections/contrib/old_work_creator/admin/creator.py
glamkit_collections/contrib/old_work_creator/admin/image.py
glamkit_collections/contrib/old_work_creator/admin/work.py
glamkit_collections/contrib/old_work_creator/models/__init__.py
glamkit_collections/contrib/old_work_creator/models/creator.py
glamkit_collections/contrib/old_work_creator/models/image.py
glamkit_collections/contrib/old_work_creator/models/other.py
glamkit_collections/contrib/old_work_creator/models/work.py
glamkit_collections/contrib/work_creator/__init__.py
glamkit_collections/contrib/work_creator/admin.py
glamkit_collections/contrib/work_creator/apps.py
glamkit_collections/contrib/work_creator/managers.py
glamkit_collections/contrib/work_creator/models.py
glamkit_collections/contrib/work_creator/plugins.py
glamkit_collections/contrib/work_creator/migrations/0001_initial.py
glamkit_collections/contrib/work_creator/migrations/0002_workbase_department.py
glamkit_collections/contrib/work_creator/migrations/0003_auto_20161026_1606.py
glamkit_collections/contrib/work_creator/migrations/0004_auto_20161026_1828.py
glamkit_collections/contrib/work_creator/migrations/0005_workbase_images.py
glamkit_collections/contrib/work_creator/migrations/0006_auto_20161026_2259.py
glamkit_collections/contrib/work_creator/migrations/0007_auto_20161028_1904.py
glamkit_collections/contrib/work_creator/migrations/__init__.py
glamkit_collections/contrib/work_creator/plugins/__init__.py
glamkit_collections-0.36.dist-info/DESCRIPTION.rst
glamkit_collections-0.36.dist-info/METADATA
glamkit_collections-0.36.dist-info/RECORD
glamkit_collections-0.36.dist-info/WHEEL
glamkit_collections-0.36.dist-info/metadata.json
glamkit_collections-0.36.dist-info/top_level.txt
