Metadata-Version: 2.0
Name: glamkit-collections
Version: 0.36
Summary: Boilerplate for modelling collections of collecting institutions.
Home-page: https://github.com/ixc/glamkit-collections
Author: Interaction Consortium
Author-email: studio@interaction.net.au
License: UNKNOWN
Platform: UNKNOWN
Requires-Dist: Django (>=1.7)
Requires-Dist: django-admin-sortable2
Requires-Dist: django-icekit
Requires-Dist: django-object-actions (>=0.7)
Requires-Dist: pyparsing
Requires-Dist: unidecode
Provides-Extra: colors
Requires-Dist: colormath (==2.1.1); extra == 'colors'
Requires-Dist: colorweave (==0.1+0.ce27c83b4e06a8185531538fa11c18c5ea2c1aba.ixc); extra == 'colors'
Requires-Dist: webcolors (==1.5); extra == 'colors'
